src/__init__.py
src/plugin.py
mkdocs_tablestrip-1.0.4.dist-info/LICENSE.txt
mkdocs_tablestrip-1.0.4.dist-info/METADATA
mkdocs_tablestrip-1.0.4.dist-info/WHEEL
mkdocs_tablestrip-1.0.4.dist-info/entry_points.txt
mkdocs_tablestrip-1.0.4.dist-info/top_level.txt
mkdocs_tablestrip-1.0.4.dist-info/RECORD
