Metadata-Version: 2.1
Name: mkdocs-tablestrip
Version: 1.0.4
Summary: This mkdocs plugin allows you to strip rows from tables across your documentation.
Author-email: CyberOtter <baum.np79a@slmail.me>
Project-URL: Homepage, https://github.com/SaltyAimbOtter/mkdocs-tablestrip
Project-URL: Bug Tracker, https://github.com/SaltyAimbOtter/mkdocs-tablestrip/issues
Keywords: mkdocs,table,strip,data,documentation
Classifier: Development Status :: 5 - Production/Stable
Classifier: Intended Audience :: Developers
Classifier: Intended Audience :: Information Technology
Classifier: License :: OSI Approved :: MIT License
Classifier: Programming Language :: Python
Classifier: Programming Language :: Python :: 3 :: Only
Requires-Python: >=3.7
License-File: LICENSE.txt
Requires-Dist: mkdocs>=1.6.0
Requires-Dist: beautifulsoup4>=4.12.3
